vastgenserver.cpython-310-x86_64-linux-gnu.so
vastgenserver.cpython-313-x86_64-linux-gnu.so
vastgenserver.cpython-38-x86_64-linux-gnu.so
vastgenserver.pyi
vastgenserver.build/.gitignore
vastgenserver_dev-0.5.1.dist-info/METADATA
vastgenserver_dev-0.5.1.dist-info/WHEEL
vastgenserver_dev-0.5.1.dist-info/entry_points.txt
vastgenserver_dev-0.5.1.dist-info/top_level.txt
vastgenserver_dev-0.5.1.dist-info/RECORD
